Products.ZMySQLDA-6.1-py3.13-nspkg.pth
Products/ZMySQLDA/DA.py
Products/ZMySQLDA/__init__.py
Products/ZMySQLDA/db.py
Products/ZMySQLDA/permissions.py
Products/ZMySQLDA/utils.py
Products/ZMySQLDA/tests/__init__.py
Products/ZMySQLDA/tests/base.py
Products/ZMySQLDA/tests/dummy.py
Products/ZMySQLDA/tests/test_DA.py
Products/ZMySQLDA/tests/test_db.py
Products/ZMySQLDA/tests/test_utils.py
Products/ZMySQLDA/www/bin.gif
Products/ZMySQLDA/www/bin.svg
Products/ZMySQLDA/www/browse.dtml
Products/ZMySQLDA/www/connectionAdd.dtml
Products/ZMySQLDA/www/connectionEdit.dtml
Products/ZMySQLDA/www/da.gif
Products/ZMySQLDA/www/da.svg
Products/ZMySQLDA/www/date.gif
Products/ZMySQLDA/www/date.svg
Products/ZMySQLDA/www/datetime.gif
Products/ZMySQLDA/www/datetime.svg
Products/ZMySQLDA/www/field.gif
Products/ZMySQLDA/www/field.svg
Products/ZMySQLDA/www/float.gif
Products/ZMySQLDA/www/float.svg
Products/ZMySQLDA/www/int.gif
Products/ZMySQLDA/www/int.svg
Products/ZMySQLDA/www/stable.gif
Products/ZMySQLDA/www/stable.svg
Products/ZMySQLDA/www/table.gif
Products/ZMySQLDA/www/table.svg
Products/ZMySQLDA/www/table_info.dtml
Products/ZMySQLDA/www/text.gif
Products/ZMySQLDA/www/text.svg
Products/ZMySQLDA/www/time.gif
Products/ZMySQLDA/www/time.svg
Products/ZMySQLDA/www/view.gif
Products/ZMySQLDA/www/view.svg
Products/ZMySQLDA/www/what.gif
Products/ZMySQLDA/www/what.svg
products_zmysqlda-6.1.dist-info/licenses/LICENSE.txt
products_zmysqlda-6.1.dist-info/METADATA
products_zmysqlda-6.1.dist-info/WHEEL
products_zmysqlda-6.1.dist-info/namespace_packages.txt
products_zmysqlda-6.1.dist-info/top_level.txt
products_zmysqlda-6.1.dist-info/RECORD
